README.txt
setup.cfg
setup.py
italianskin/__init__.py
italianskin.templates.egg-info/PKG-INFO
italianskin.templates.egg-info/SOURCES.txt
italianskin.templates.egg-info/dependency_links.txt
italianskin.templates.egg-info/entry_points.txt
italianskin.templates.egg-info/namespace_packages.txt
italianskin.templates.egg-info/not-zip-safe
italianskin.templates.egg-info/requires.txt
italianskin.templates.egg-info/top_level.txt
italianskin/templates/__init__.py
italianskin/templates/config.py
italianskin/templates/interfaces.py
italianskin/templates/setuphandlers.py
italianskin/templates/tests.py
italianskin/templates/validators_utils.py
italianskin/templates/browser/__init__.py
italianskin/templates/browser/plone/__init__.py
italianskin/templates/browser/plone/app/__init__.py
italianskin/templates/browser/plone/app/content/__init__.py
italianskin/templates/browser/plone/app/content/browser/__init__.py
italianskin/templates/browser/plone/app/content/browser/foldercontents.py
italianskin/templates/browser/plone/app/contentmenu/__init__.py
italianskin/templates/browser/plone/app/contentmenu/view.py
italianskin/templates/browser/plone/app/contentrules/__init__.py
italianskin/templates/browser/plone/app/contentrules/browser/__init__.py
italianskin/templates/browser/plone/app/contentrules/browser/controlpanel.py
italianskin/templates/browser/plone/app/controlpanel/__init__.py
italianskin/templates/browser/plone/app/controlpanel/form.py
italianskin/templates/browser/plone/app/controlpanel/maintenance.py
italianskin/templates/browser/plone/app/controlpanel/types.py
italianskin/templates/browser/plone/app/layout/__init__.py
italianskin/templates/browser/plone/app/layout/viewlets/__init__.py
italianskin/templates/browser/plone/app/layout/viewlets/comments.py
italianskin/templates/browser/plone/app/layout/viewlets/common.py
italianskin/templates/browser/plone/app/layout/viewlets/fake_i18n.py
italianskin/templates/browser/plone/app/portlets/__init__.py
italianskin/templates/browser/plone/app/portlets/portlets/__init__.py
italianskin/templates/browser/plone/app/workflow/__init__.py
italianskin/templates/browser/plone/app/workflow/browser/__init__.py
italianskin/templates/browser/plone/app/workflow/browser/kss_sharing.py
italianskin/templates/browser/plone/app/workflow/browser/sharing.py