Metadata-Version: 1.0
Name: italianskin.templates
Version: 3.3.5
Summary: italianskin XHTML Strict templates for Plone
Home-page: http://www.redomino.com/it/labs/progetti/ItalianSkin
Author: davide moro
Author-email: davide.moro@redomino.com
License: GPL
Keywords: web zope plone theme
Platform: UNKNOWN
Classifier: Framework :: Plone
Classifier: Framework :: Zope2
Classifier: Framework :: Zope3
Classifier: Programming Language :: Python
Classifier: Topic :: Software Development :: Libraries :: Python Modules
